odoo/addons/delivery_dhl_parcel/README.rst
odoo/addons/delivery_dhl_parcel/__init__.py
odoo/addons/delivery_dhl_parcel/__manifest__.py
odoo/addons/delivery_dhl_parcel/doc/Documento_integracion_WEB_SERVICE_B2B_B2C_ver6.pdf
odoo/addons/delivery_dhl_parcel/i18n/delivery_dhl_parcel.pot
odoo/addons/delivery_dhl_parcel/i18n/es.po
odoo/addons/delivery_dhl_parcel/models/__init__.py
odoo/addons/delivery_dhl_parcel/models/delivery_carrier.py
odoo/addons/delivery_dhl_parcel/models/dhl_parcel_request.py
odoo/addons/delivery_dhl_parcel/models/stock_picking.py
odoo/addons/delivery_dhl_parcel/readme/CONFIGURE.rst
odoo/addons/delivery_dhl_parcel/readme/CONTRIBUTORS.rst
odoo/addons/delivery_dhl_parcel/readme/DESCRIPTION.rst
odoo/addons/delivery_dhl_parcel/readme/INSTALL.rst
odoo/addons/delivery_dhl_parcel/readme/ROADMAP.rst
odoo/addons/delivery_dhl_parcel/readme/USAGE.rst
odoo/addons/delivery_dhl_parcel/static/description/icon.png
odoo/addons/delivery_dhl_parcel/static/description/index.html
odoo/addons/delivery_dhl_parcel/tests/__init__.py
odoo/addons/delivery_dhl_parcel/tests/test_delivery_dhl_parcel.py
odoo/addons/delivery_dhl_parcel/views/delivery_carrier_view.xml
odoo/addons/delivery_dhl_parcel/views/stock_picking_views.xml
odoo/addons/delivery_dhl_parcel/wizard/__init__.py
odoo/addons/delivery_dhl_parcel/wizard/dhl_parcel_end_day_wizard.py
odoo/addons/delivery_dhl_parcel/wizard/dhl_parcel_end_day_wizard_views.xml
odoo13_addon_delivery_dhl_parcel-13.0.1.3.4.dist-info/METADATA
odoo13_addon_delivery_dhl_parcel-13.0.1.3.4.dist-info/WHEEL
odoo13_addon_delivery_dhl_parcel-13.0.1.3.4.dist-info/top_level.txt
odoo13_addon_delivery_dhl_parcel-13.0.1.3.4.dist-info/RECORD
