Metadata-Version: 2.1
Name: odoo13-addon-delivery-dhl-parcel
Version: 13.0.1.3.4
Summary: Delivery Carrier implementation for DHL Parcel using their API
Home-page: https://github.com/OCA/l10n-spain
Author: Studio73, Odoo Community Association (OCA)
Author-email: support@odoo-community.org
License: AGPL-3
Platform: UNKNOWN
Classifier: Programming Language :: Python
Classifier: Framework :: Odoo
Classifier: Framework :: Odoo :: 13.0
Classifier: License :: OSI Approved :: GNU Affero General Public License v3
Requires-Python: >=3.5
Requires-Dist: odoo13-addon-delivery-package-number
Requires-Dist: odoo13-addon-delivery-state
Requires-Dist: odoo (<13.1dev,>=13.0a)
